claia/__init__.py
claia/__main__.py
claia/manager.py
claia/registry.py
claia/agents/__init__.py
claia/agents/simple.py
claia/architectures/__init__.py
claia/architectures/anthropic.py
claia/architectures/dummy.py
claia/architectures/openai.py
claia/architectures/transformers_gemma3.py
claia/architectures/transformers_generic.py
claia/cli/__init__.py
claia/cli/__main__.py
claia/cli/agents.py
claia/cli/defaults.py
claia/cli/logger.py
claia/cli/settings.py
claia/cli/utils.py
claia/cli/commands/__init__.py
claia/cli/commands/agent.py
claia/cli/commands/base.py
claia/cli/commands/conversation.py
claia/cli/commands/core.py
claia/cli/commands/get_set.py
claia/cli/commands/model.py
claia/cli/commands/query.py
claia/cli/commands/setup.py
claia/cli/commands/specs.py
claia/cli/commands/system.py
claia/cli/commands/tool.py
claia/definitions/__init__.py
claia/definitions/anthropic.py
claia/definitions/legacy.py
claia/definitions/openai.py
claia/deployments/__init__.py
claia/deployments/api.py
claia/deployments/dummy.py
claia/deployments/local.py
claia/deployments/remote.py
claia/hooks/__init__.py
claia/hooks/agent.py
claia/hooks/architecture.py
claia/hooks/definition.py
claia/hooks/deployment.py
claia/hooks/pattern.py
claia/hooks/protocol.py
claia/hooks/solver.py
claia/hooks/tool.py
claia/lib/__init__.py
claia/lib/base.py
claia/lib/process.py
claia/lib/queue.py
claia/lib/results.py
claia/lib/data/__init__.py
claia/lib/data/models/__init__.py
claia/lib/data/models/audio.py
claia/lib/data/models/base.py
claia/lib/data/models/image.py
claia/lib/data/models/prompt.py
claia/lib/data/models/text.py
claia/lib/data/models/conversation/__init__.py
claia/lib/data/models/conversation/action.py
claia/lib/data/models/conversation/conversation.py
claia/lib/data/models/conversation/conversation_settings.py
claia/lib/data/models/conversation/message.py
claia/lib/data/models/conversation/tool_definition.py
claia/lib/data/repositories/__init__.py
claia/lib/data/repositories/base.py
claia-0.1.8.dist-info/licenses/LICENSE
claia-0.1.8.dist-info/licenses/NOTICE
claia-0.1.8.dist-info/METADATA
claia-0.1.8.dist-info/WHEEL
claia-0.1.8.dist-info/entry_points.txt
claia-0.1.8.dist-info/top_level.txt
claia-0.1.8.dist-info/RECORD
