Metadata-Version: 2.4
Name: claia
Version: 0.1.8
Summary: CLAIA Framework
Author: Lloyd Bower, ExoFox, LLC
License: 
Project-URL: Homepage, https://claia.dev
Project-URL: Repository, https://gitlab.com/exofox/claia/claia.git
Project-URL: Issues, https://gitlab.com/exofox/claia/claia/-/issues
Classifier: Development Status :: 2 - Pre-Alpha
Classifier: Programming Language :: Python :: 3
Classifier: Programming Language :: Python :: 3.12
Classifier: License :: OSI Approved :: Apache Software License
Classifier: Operating System :: OS Independent
Classifier: Intended Audience :: Developers
Classifier: Topic :: Software Development :: Libraries
Requires-Python: >=3.12
License-File: LICENSE
License-File: NOTICE
Requires-Dist: torch
Requires-Dist: diffusers
Requires-Dist: transformers>=4.50.0
Requires-Dist: aia
Requires-Dist: beautifulsoup4
Requires-Dist: chardet
Requires-Dist: python-dotenv
Requires-Dist: pluggy
Requires-Dist: requests
Requires-Dist: pyreadline3
Requires-Dist: pyfiglet
Dynamic: license-file
